sphinx_xml2rfc/__init__.py
sphinx_xml2rfc/autogen.py
sphinx_xml2rfc/domain.py
sphinx_xml2rfc/utils.py
sphinx_xml2rfc-0.1.0.dist-info/LICENSE
sphinx_xml2rfc-0.1.0.dist-info/METADATA
sphinx_xml2rfc-0.1.0.dist-info/WHEEL
sphinx_xml2rfc-0.1.0.dist-info/top_level.txt
sphinx_xml2rfc-0.1.0.dist-info/RECORD
