Metadata-Version: 2.1
Name: sphinx-xml2rfc
Version: 0.1.0
Summary: A sphinx extension for documenting IETF Internet-Draft versions
Home-page: https://github.com/benmaddison/sphinx-xml2rfc
Author: Ben Maddison
Author-email: benm@workonline.africa
License: MIT
Project-URL: Documentation, https://benmaddison.github.io/sphinx-xml2rfc
Project-URL: Bug Tracker, https://github.com/benmaddison/sphinx-xml2rfc/issues
Keywords: ietf,xml2rfc
Platform: UNKNOWN
Classifier: Development Status :: 4 - Beta
Classifier: Framework :: Sphinx
Classifier: Framework :: Sphinx :: Extension
Classifier: Intended Audience :: Telecommunications Industry
Classifier: License :: OSI Approved :: MIT License
Classifier: Natural Language :: English
Classifier: Operating System :: OS Independent
Classifier: Programming Language :: Python :: 3
Classifier: Programming Language :: Python :: 3.8
Classifier: Programming Language :: Python :: 3.9
Classifier: Topic :: Documentation
Classifier: Topic :: Documentation :: Sphinx
Classifier: Topic :: Internet
Classifier: Topic :: Software Development :: Documentation
Classifier: Topic :: Software Development :: Version Control :: Git
Classifier: Typing :: Typed
Requires-Python: >=3.8
License-File: LICENSE
Requires-Dist: GitPython (>=3.1.17)
Requires-Dist: xml2rfc (>=3.8.0)
Requires-Dist: Sphinx (>=3.5.4)
